toa_extractor/__init__.py
toa_extractor/_astropy_init.py
toa_extractor/conftest.py
toa_extractor/data_setup.py
toa_extractor/pipeline.py
toa_extractor/plotting.py
toa_extractor/status.py
toa_extractor/summary.py
toa_extractor/toa_stats.py
toa_extractor/version.py
toa_extractor/data/README.rst
toa_extractor/data/crab_512.ecsv
toa_extractor/data/crab_nustar_cr250.ecsv
toa_extractor/data/jb_crab_glitches.ecsv
toa_extractor/data/templates.yaml
toa_extractor/extern/__init__.py
toa_extractor/tests/__init__.py
toa_extractor/tests/test_pipeline.py
toa_extractor/tests/test_toa_stats.py
toa_extractor/tests/data/astrosat_test.fits
toa_extractor/tests/data/nicer_test.evt
toa_extractor/tests/data/nustar_test.evt.gz
toa_extractor/utils/__init__.py
toa_extractor/utils/base.py
toa_extractor/utils/config.py
toa_extractor/utils/crab.py
toa_extractor/utils/data_manipulation.py
toa_extractor/utils/fftfit.py
toa_extractor/utils/fit_crab_profiles.py
toa_extractor/utils/fold.py
toa_extractor/utils/tests/__init__.py
toa_extractor/utils/tests/test_base.py
toa_extractor/utils/tests/test_crab.py
toa_extractor/utils/tests/test_fit_crab_profiles.py
toa_extractor-0.6.0.dist-info/LICENSE.rst
toa_extractor-0.6.0.dist-info/METADATA
toa_extractor-0.6.0.dist-info/WHEEL
toa_extractor-0.6.0.dist-info/entry_points.txt
toa_extractor-0.6.0.dist-info/top_level.txt
toa_extractor-0.6.0.dist-info/RECORD
