Metadata-Version: 2.1
Name: toa_extractor
Version: 0.6.0
Summary: Calculate TOAs and residuals of pulsars
Home-page: https://github.com/matteobachetti/toa_extractor
Author: Matteo Bachetti
Author-email: matteo@matteobachetti.it
License: BSD 3-Clause
Requires-Python: >=3.9
License-File: licenses/LICENSE.rst
Requires-Dist: numba
Requires-Dist: numpy
Requires-Dist: scipy
Requires-Dist: statsmodels
Requires-Dist: astropy
Requires-Dist: astroquery
Requires-Dist: matplotlib
Requires-Dist: uncertainties
Requires-Dist: luigi
Requires-Dist: pyyaml
Requires-Dist: pint-pulsar
Requires-Dist: h5py
Requires-Dist: bokeh >=3.5.0
Requires-Dist: stingray >2.2.8
Requires-Dist: hendrics >=8.0.4
Requires-Dist: pulse-deadtime-fix
Provides-Extra: docs
Requires-Dist: sphinx-astropy ; extra == 'docs'
Provides-Extra: test
Requires-Dist: pytest-astropy ; extra == 'test'
